picpay/__init__.py
picpay/__version__.py
picpay/download.py
picpay/picpay.py
picpay-1.1.1.dist-info/LICENSE
picpay-1.1.1.dist-info/WHEEL
picpay-1.1.1.dist-info/METADATA
picpay-1.1.1.dist-info/RECORD
