Metadata-Version: 2.1
Name: picpay
Version: 1.1.1
Summary: 
Home-page: https://github.com/MarcusMann/picpay.py
License: MIT
Keywords: picpay,gateway de pagamento,loja virtual,ecommerce,pagseguro
Author: Marcus Pereira
Author-email: oi@spacedevs.com.br
Requires-Python: >=3.8,<4.0
Classifier: License :: OSI Approved :: MIT License
Classifier: Programming Language :: Python :: 3
Classifier: Programming Language :: Python :: 3.8
Requires-Dist: requests (>=2.22.0,<3.0.0)
Project-URL: Repository, https://github.com/MarcusMann/picpay.py
